pathsimanalysis/__init__.py
pathsimanalysis/psa.py
pathsimanalysis/tests/__init__.py
pathsimanalysis/tests/test_pathsimanalysis.py
pathsimanalysis-1.1.0.dist-info/AUTHORS.md
pathsimanalysis-1.1.0.dist-info/LICENSE
pathsimanalysis-1.1.0.dist-info/METADATA
pathsimanalysis-1.1.0.dist-info/WHEEL
pathsimanalysis-1.1.0.dist-info/top_level.txt
pathsimanalysis-1.1.0.dist-info/RECORD
